heartale/__init__.py
heartale/servers/__init__.py
heartale/servers/legado.py
heartale/servers/txt.py
heartale/tools/__init__.py
heartale/tools/cache.py
heartale/tools/config.py
heartale/tools/constant.py
heartale/tools/count.py
heartale/tts/__init__.py
heartale/tts/coqui.py
heartale/tts/edge.py
heartale/tts/g_tts.py
heartale/tts/ms_azure.py
heartale/tts/paddle_speech.py
heartale/tts/fish/__init__.py
heartale/tts/fish/commons.py
heartale/tts/fish/file.py
heartale-0.0.2.dist-info/METADATA
heartale-0.0.2.dist-info/WHEEL
heartale-0.0.2.dist-info/entry_points.txt
heartale-0.0.2.dist-info/top_level.txt
heartale-0.0.2.dist-info/RECORD
