Metadata-Version: 2.4
Name: heartale
Version: 0.0.2
Summary: 听书
Author-email: yuhldr <yuhldr@qq.com>
Requires-Dist: edge_tts>=6.1.13
Requires-Dist: aiohttp
